<odoo>
    <data noupdate="1">
        <record id="cron_check_overdue_loans" model="ir.cron">
            <field name="name">Verificar Préstamos Vencidos</field>
            <field name="model_id" ref="model_stock_picking"/>
            <field name="state">code</field>
            <field name="code">model._cron_check_overdue_loans()</field>
            <field name="user_id" ref="base.user_root"/>
            <field name="interval_number">1</field>
            <field name="interval_type">days</field>
            <field name="active" eval="True"/>
        </record>

        <record id="cron_process_overdue_risk_entries" model="ir.cron">
            <field name="name">Procesar Asientos de Riesgo</field>
            <field name="model_id" ref="model_loan_accounting_manager"/>
            <field name="state">code</field>
            <field name="code">model.process_overdue_risk_entries()</field>
            <field name="user_id" ref="base.user_root"/>
            <field name="interval_number">7</field>
            <field name="interval_type">days</field>
            <field name="active" eval="True"/>
        </record>

        <record id="cron_cleanup_old_loan_records" model="ir.cron">
            <field name="name">Limpiar Registros Antiguos de Préstamos</field>
            <field name="model_id" ref="model_loan_tracking_detail"/>
            <field name="state">code</field>
            <field name="code">model._cron_cleanup_old_resolved_records()</field>
            <field name="user_id" ref="base.user_root"/>
            <field name="interval_number">1</field>
            <field name="interval_type">months</field>
            <field name="active" eval="False"/>
        </record>
    </data>
</odoo>